[{"title": "Aeschylus' Prometheus. Met inleiding, critische noten en commentaar uitgegeven door dr. P. Groeneboom ...", "author": "Aeschylus.", "id": "1812090"}, {"title": "Aischylos' Schutzflehende, mit ausf\u00fchrlicher einleitung, text kommentar, exkursen und sach-register von dr. J. V\u00fcrtheim ...", "author": "Aeschylus.", "id": "1812116"}, {"title": "Studi\u00ebn over Aeschylus' Agamemnon ...", "author": "Hoving, Willem.", "id": "1812065"}, {"title": "Zu den Liedern des Aischylos.", "author": "Reinhard, Luise, 1880-", "id": "6561831"}, {"title": "Studi\u00ebn over Aeschylus' Agamemnon ...", "author": "Hoving, Willem.", "id": "1812065"}, {"title": "Eschyle : \u00e9tudes sur l'invention dramatique dans son th\u00e9atre / par Maurice Croiset.", "author": "Croiset, Maurice, 1846-1935.", "id": "8235220"}, {"title": "The Agamemnon of Aeschylus, an English version by Sir Henry Sharp.", "author": "Aeschylus.", "id": "8235229"}, {"title": "The seven plays in English verse, by Lewis Campbell.", "author": "Aeschylus.", "id": "100882707"}]