[{"title": "The life of Paul / by Benjamin Willard Robinson.", "author": "Robinson, Benjamin Willard, 1883-", "id": "7346637"}, {"title": "The Acts of the Apostles / with introduction and notes, by Rev. H.T.Andrews.", "author": "Andrews, H. T. 1864-1928.", "id": "103021750"}, {"title": "Die Haustafeln, ein Stu\u0308ck urchristlicher Para\u0308nese; von Karl Weidinger ...", "author": "Weidinger, Karl, 1901-", "id": "6021300"}, {"title": "Saint Paul / Ernest Renan.", "author": "Renan, Ernest, 1823-1892.", "id": "11801178"}, {"title": "Saint Paul / Ernest Renan.", "author": "Renan, Ernest, 1823-1892.", "id": "11801178"}, {"title": "Om Codex argenteus, dess tid, hem och \u00f6den / av Otto v. Friesen och Anders Grape ; med ett appendix av Hugo Andersson.", "author": "Friesen, Otto van. 1870-", "id": "1410972"}, {"title": "Jesus on social institutions,", "author": "Mathews, Shailer, 1863-1941.", "id": "1400294"}, {"title": "The Robertson codex [by] John W. Bowman ...", "author": "Bowman, John W.", "id": "1930840"}, {"title": "Notes on St. Luke and the Acts, by Alex, Pallis.", "author": "Pall\u0113s, Alexandros, 1851-1935.", "id": "1938453"}, {"title": "Kitab p\u0115rjanjian baharu.", "author": "", "id": "1937483"}, {"title": "The complete commentary of Oecumenius on the Apocalypse / edited with notes by H. C. Hoskier.", "author": "Oecumenius, Bishop of Tricca", "id": "1411408"}, {"title": "Studies in New Testament Christianity.", "author": "Barton, George A. 1859-1942.", "id": "1410813"}, {"title": "The text of Revelation; a revised theory, by John Oman ...", "author": "", "id": "1924356"}, {"title": "The general epistles, James, Peter, and Judas / by James Moffatt.", "author": "Moffatt, James, 1870-1944.", "id": "1400399"}, {"title": "The gospel and its tributaries,", "author": "Scott, Ernest Findlay, 1868-1954.", "id": "1400260"}, {"title": "The challenge of Christ / by Florence Schleicher.", "author": "Teed, Florence Ernestine Schleicher, 1901-1954.", "id": "3151059"}, {"title": "The challenge of Christ / by Florence Schleicher.", "author": "Teed, Florence Ernestine Schleicher, 1901-1954.", "id": "3151059"}, {"title": "The challenge of Christ / by Florence Schleicher.", "author": "Teed, Florence Ernestine Schleicher, 1901-1954.", "id": "3151059"}, {"title": "The Caesarean text of the Gospel of Mark [by] Kirsopp Lake and Robert P. Blake ... and Silva New ...", "author": "Lake, Kirsopp, 1872-1946.", "id": "1938409"}, {"title": "The synoptic gospels edited with an introduction and a commentary", "author": "Montefiore, C. G. 1858-1938", "id": "1411002"}, {"title": "The synoptic gospels edited with an introduction and a commentary", "author": "Montefiore, C. G. 1858-1938", "id": "1411002"}, {"title": "A history of Christianity in the apostolic age by Arthur Cushman McGiffert.", "author": "McGiffert, Arthur Cushman, 1861-1933.", "id": "100459316"}, {"title": "The general epistles, James, Peter, and Judas, by James Moffatt.", "author": "Moffatt, James, 1870-1944.", "id": "6605643"}, {"title": "The heresy of Antioch, an interpretation, by Robert Norwood.", "author": "Norwood, Robert Winkworth, 1874-1932.", "id": "6606403"}, {"title": "The glorious company; lives and legends of the twelve and St. Paul, by Tracy D. Mygatt, Frances Witherspoon, with drawings by Charles O. Naef.", "author": "Mygatt, Tracy D. 1885-1973.", "id": "5765509"}, {"title": "Erweckung und Gefolgschaft im Urchristentum, von Fritz Cronheim.", "author": "Godfrey, Frederick M.", "id": "6500088"}, {"title": "The Epistles of Paul the apostle to the Colossians and the Philemon, ed. by A. Lukyn Williams ... with introduction and notes.", "author": "", "id": "6525549"}, {"title": "Greek thought in the New Testament.", "author": "Gilbert, George Holley, 1854-1930.", "id": "6529779"}, {"title": "U\u0308bungsbuch zur einfu\u0308hrung in die textgeschichte des Neuen Testamentes, von dr. Heinrich Joseph Vogels.", "author": "Vogels, Heinrich Joseph, b. 1880.", "id": "6561796"}, {"title": "The Caesarean text of the Gospel of Mark [by] Kirsopp Lake and Robert P. Blake ... and Silva New ...", "author": "Lake, Kirsopp, 1872-1946.", "id": "1938409"}, {"title": "And was made man, and introduction to the study of the Gospels,", "author": "Hodgson, Leonard, 1889-1969", "id": "7128249"}, {"title": "And was made man, and introduction to the study of the Gospels,", "author": "Hodgson, Leonard, 1889-1969", "id": "7128249"}, {"title": "In Epistolas ad Romanos et I. ad Corinthios.", "author": "Lapide, Cornelius \u00e0, 1567-1637.", "id": "7853404"}, {"title": "Studies in New Testament Christianity.", "author": "Barton, George A. 1859-1942.", "id": "1410813"}, {"title": "Transactions of the Dental Society of the State of New York.", "author": "Dental Society of the State of New York.", "id": "6216706"}, {"title": "An exegetical commentary on the Gospel according to S. Matthew, by the Rev. Alfred Plummer.", "author": "Plummer, Alfred, 1841-1926.", "id": "102156188"}, {"title": "Lives and legends of apostles and evangelists, by Myrtle Strode-Jackson.", "author": "Jackson, Myrtle Strode.", "id": "102870636"}, {"title": "The New Testament church, its teaching and its Scriptures.", "author": "Miller, Park Hays, 1879-", "id": "102300293"}, {"title": "The philosophy of Jesus, the basis of a new reformation,", "author": "Edgerton, James Arthur, 1869-1938.", "id": "8374850"}, {"title": "A harmony of the sysnoptic Gospels in Greek,", "author": "", "id": "8374578"}, {"title": "The text of the New Testament,", "author": "Lake, Kirsopp, 1872-1946.", "id": "8374144"}, {"title": "L'Apo\u0302tre Saint Jean.", "author": "Baunard, Mgr., 1826-1919.", "id": "100618830"}, {"title": "The gospel before the Gospels, by Burton Scott Easton.", "author": "Easton, Burton Scott, 1877-1950.", "id": "102065325"}, {"title": "A critical and exegetical commentary on the Gospel according to St. John, by J.H. Bernard, edited by A.H. McNeile.", "author": "Bernard, J. H. 1860-1927.", "id": "101926644"}, {"title": "A critical and exegetical commentary on the Gospel according to St. John, by J.H. Bernard, edited by A.H. McNeile.", "author": "Bernard, J. H. 1860-1927.", "id": "101926644"}, {"title": "The Gospel of Matthew / by Theodore H. Robinson.", "author": "Robinson, Theodore H. 1881-1964", "id": "102092830"}, {"title": "The Epistle of Paul to the Philippians, by the Rev. J. Hugh Michael.", "author": "Michael, John Hugh, 1878-", "id": "102098676"}, {"title": "The drama of Christianity : an interpretation of the Apocalypse / by [S. L. Morris]", "author": "Morris, S. L. 1854-1937.", "id": "102098008"}, {"title": "Preaching values in new translations of the New Testament, by Halford E. Luccock.", "author": "Luccock, Halford Edward, 1885-1960.", "id": "102044537"}, {"title": "The Gospel of Matthew / by Theodore H. Robinson.", "author": "Robinson, Theodore H. 1881-1964", "id": "102045422"}, {"title": "Commentary on the four gospels : in three volumes / by David Smith.", "author": "Smith, David, 1866-1932.", "id": "102046178"}, {"title": "The First epistle of Paul to the Corinthians; an exposition, by Charles R. Erdman.", "author": "Erdman, Charles R. 1866-1960", "id": "102055999"}, {"title": "The general epistles, James, Peter, and Judas.", "author": "Moffatt, James, 1870-1944.", "id": "102098680"}, {"title": "The text of the New Testament,", "author": "Lake, Kirsopp, 1872-1946.", "id": "8374144"}, {"title": "The complete commentary of Oecumenius on the Apocalypse / edited with notes by H. C. Hoskier.", "author": "Oecumenius, Bishop of Tricca", "id": "1411408"}, {"title": "The glorious company; lives and legends of the twelve and St. Paul, by Tracy D. Mygatt, Frances Witherspoon, with drawings by Charles O. Naef.", "author": "Mygatt, Tracy D. 1885-1973.", "id": "5765509"}, {"title": "The synoptic gospels edited with an introduction and a commentary", "author": "Montefiore, C. G. 1858-1938", "id": "1411002"}, {"title": "The synoptic gospels edited with an introduction and a commentary", "author": "Montefiore, C. G. 1858-1938", "id": "1411002"}, {"title": "The Caesarean text of the Gospel of Mark [by] Kirsopp Lake and Robert P. Blake ... and Silva New ...", "author": "Lake, Kirsopp, 1872-1946.", "id": "1938409"}, {"title": "Notes on St. Luke and the Acts.", "author": "Palle\u0304s, Alexandros, 1851-1935.", "id": "5767177"}]