[{"title": "Promotion and retirement in the army. Hearings before the Committee on military affairs, United States Senate, Seventieth Congress, first session, on S. 1894, a bill to increase the efficiency of the army and for other purposes.", "author": "United States. Congress. Senate. Committee on Military Affairs.", "id": "101700697"}, {"title": "Promotion and retirement in the army. Hearings before the Committee on military affairs, United States Senate, Seventieth Congress, first session, on S. 1894, a bill to increase the efficiency of the army and for other purposes.", "author": "United States. Congress. Senate. Committee on Military Affairs.", "id": "101700697"}, {"title": "For the relief of Robert W. Miller : hearing ... Seventieth Congress, first session. March 31, 1928.", "author": "United States. Congress. House. Committee on Military Affairs.", "id": "100668149"}]