[{"title": "Das dorf als soziales gebilde ... hrsg. von Leopold von Wiese.", "author": "Wiese, Leopold von, 1876-1969.", "id": "9069748"}, {"title": "Rural sociological research in the United States [by C. J. Galpin and others.", "author": "Social Science Research Council (U.S.). Advisory Committee on Social and Economic Research in Agriculture.", "id": "5971387"}, {"title": "Proceedings of the National Country Life Conference.", "author": "National Country Life Conference.", "id": "6068760"}, {"title": "Rural sociological research in the United States. A social science research monograph.", "author": "Social Science Research Council (U.S.) Advisory Committee on Economics and Social Research in Agriculture.", "id": "1741767"}, {"title": "Elements of rural sociology,", "author": "Sims, Newell Le Roy, 1878-", "id": "1130518"}, {"title": "Proceedings of the ... Conference of the American Country Life Association, Inc.", "author": "American Country Life Association. Conference.", "id": "495695"}, {"title": "Handbook of rural social resources.", "author": "", "id": "2131473"}, {"title": "Proceedings of the National Country Life Conference.", "author": "National Country Life Conference.", "id": "6068760"}, {"title": "Proceedings of the National Country Life Conference.", "author": "National Country Life Conference.", "id": "6068760"}, {"title": "Proceedings of the National Country Life Conference.", "author": "National Country Life Conference.", "id": "6068760"}, {"title": "Handbook of rural social resources ...", "author": "", "id": "2131473"}, {"title": "A decade of rural progress, based on: Reports of committees to the American country life association; Proceedings of the tenth National country life conference; Proceedings of the eleventh National country life conference ed. by B. Y. Landis and N. T. Frame.", "author": "Landis, Benson Y. 1897-", "id": "6556360"}, {"title": "Proceedings of the conference of the American Country Life Association.", "author": "American Country Life Conference.", "id": "100120058"}, {"title": "Proceedings", "author": "American Country Life Association.", "id": "9996631"}, {"title": "Rural sociology, by John Morris Gillette.", "author": "Gillette, John Morris, 1866-", "id": "101851062"}, {"title": "Laboratory manual and exercises in rural community problems, for use in rural life, rural sociology, and rural community courses ... by S.C. Ratcliffe ... and L.W. Hacker ...", "author": "Ratcliffe, S. C.", "id": "102092187"}, {"title": "Proceedings of the conference of the American Country Life Association.", "author": "American Country Life Conference.", "id": "100120058"}, {"title": "Introduction to rural sociology, by Paul L. Vogt ...", "author": "Vogt, Paul L. 1878-", "id": "102025703"}, {"title": "Proceedings of the National Country Life Conference.", "author": "National Country Life Conference.", "id": "6068760"}, {"title": "Rural sociological research in the United States [by C. J. Galpin and others.", "author": "Social Science Research Council (U.S.). Advisory Committee on Social and Economic Research in Agriculture.", "id": "5971387"}, {"title": "Elements of rural sociology,", "author": "Sims, Newell Le Roy, 1878-", "id": "1130518"}, {"title": "Rural life in Maine, by Henry E. Dunnack.", "author": "Dunnack, Henry E. b. 1867.", "id": "6773156"}]