[{"title": "Men are like that, by Leonard Ramsden Hartill.", "author": "Hartill, Leonard Ramsden.", "id": "6045454"}, {"title": "Men are like that, by Leonard Ramsden Hartill.", "author": "Hartill, Leonard Ramsden.", "id": "1865661"}, {"title": "Hayastani Hanrapetut\u02bbiwn / S. Vrats\u02bbean.", "author": "Vrats\u02bbean, Simon, 1884-1969.", "id": "2705356"}, {"title": "Hayastani Hanrapetut\u02bbiwn / S. Vrats\u02bbean.", "author": "Vrats\u02bbean, Simon, 1884-1969.", "id": "2705356"}, {"title": "Men are like that, by Leonard Ramsden Hartill.", "author": "Hartill, Leonard Ramsden.", "id": "1865661"}, {"title": "E\u0301tudes historiques sur le peuple arme\u0301nien.", "author": "Aslan, Kevork, b. 1849.", "id": "6770650"}]