[{"title": "Massillon, once upon a time.", "author": "Skinner, Bessie V. R.", "id": "102751250"}, {"title": "Annual report of the Historical and Philosophical Society of Ohio.", "author": "Historical and Philosophical Society of Ohio.", "id": "7864163"}, {"title": "History of southeastern Ohio and the Muskingum Valley, 1788-1928; covering Athens, Belmont, Coshocton, Guernsey, Licking, Meigs, Monroe, Morgan, Muskingum, Noble, Perry and Washington counties.", "author": "Lewis, Thomas W. 1851-", "id": "6785674"}, {"title": "Ohio history.", "author": "", "id": "522266"}, {"title": "Negroes in Columbus,", "author": "Mark, Mary Louise, 1878-", "id": "1668277"}, {"title": "Columbus city directory.", "author": "", "id": "100114316"}, {"title": "Ohio arch\u00e6ological and historical quarterly", "author": "", "id": "6173591"}, {"title": "Ohio arch\u00e6ological and historical quarterly", "author": "", "id": "6173591"}]