[{"title": "Ecology", "author": "", "id": "640787"}, {"title": "Holznahrung und symbiose; vortrag gehalten auf dem x. Internationalen zoologentag zu Budapest am 8. september 1927, von Paul Buchner ... Mit 22 abbildungen.", "author": "Buchner, Paul, 1886-", "id": "1507886"}, {"title": "Ecology", "author": "", "id": "640787"}, {"title": "Evolution by symbiosis, by H. Reinheimer ... With preface by the Rev. Professor H. Maurice Relton, D. D.", "author": "Reinheimer, H.", "id": "2002804"}, {"title": "La Terre et la vie.", "author": "", "id": "496297"}, {"title": "The ecology of an Hawaiian coral reef,", "author": "Edmondson, Charles Howard, 1876-", "id": "1635219"}, {"title": "The ecology of an Hawaiian coral reef,", "author": "Edmondson, Charles Howard, 1876-", "id": "1635219"}, {"title": "The ecology of an Hawaiian coral reef,", "author": "Edmondson, Charles Howard, 1876-", "id": "1635219"}, {"title": "Popolamento vegatale ed animale delle alte montagne : Relazione illustrativa delle proposte presentate dal Comitato Geografico Nazionale Italiano al Congresso internaz. di Cambridge (luglio 1928).", "author": "Comitato geografico nazionale italiano.", "id": "11453551"}, {"title": "La Terre et la vie.", "author": "", "id": "496297"}, {"title": "Urwa\u0308ld / von R.H. France\u0301.", "author": "France\u0301, R. H. 1874-1943.", "id": "7463762"}]