[{"title": "The nature of conduct, by Percival M. Symonds.", "author": "Symonds, Percival Mallon, 1893-1960.", "id": "615638"}, {"title": "Les bases psychologiques de la vie morale, par D. Parodi.", "author": "Parodi, Dominique, 1870-", "id": "615635"}, {"title": "Les bases psychologiques de la vie morale, par D. Parodi.", "author": "Parodi, Dominique, 1870-", "id": "615635"}, {"title": "Religion oder Illusion? : eine Auseinandersetzung mit dem ju\u0308ngsten Buche Professor Sig. Freuds, Die Zukunft einer Illusion / von Heinrich Haase [sic].", "author": "Hasse, Heinrich, 1884-1935.", "id": "5776146"}]