[{"title": "Le nationalisme \u00e9gyptien.", "author": "Georges-Gaulis, Berthe", "id": "6576695"}, {"title": "Great Britain in Egypt / by E. W. Polson Newman ; forword by Sir J. G. Maxwell.", "author": "Newman, E. W. Polson 1887-", "id": "1607931"}, {"title": "Great Britain in Egypt / by E. W. Polson Newman ; forword by Sir J. G. Maxwell.", "author": "Newman, E. W. Polson 1887-", "id": "1607931"}, {"title": "L'Angleterre et l'\u00c9gypte. La campagne de 1807, par G. Douin et E.C. Fawtier-Jones.", "author": "Douin, Georges, 1884-", "id": "1969363"}, {"title": "The transit of Egypt,", "author": "Elgood, Percival George, 1863-", "id": "1607917"}, {"title": "Great Britain in Egypt / by E. W. Polson Newman ; forword by Sir J. G. Maxwell.", "author": "Newman, E. W. Polson 1887-", "id": "1607931"}, {"title": "The beginnings of the Egyptian question and the rise of Mehemet Ali : a study in the diplomacy of the Napoleonic era based on researches in the British and French archives / by Shafik Ghorbal ; with a pref. by Arnold J. Toynbee.", "author": "Ghurba\u0304l, Muh\u0323ammad Shafi\u0304q, 1894-1961.", "id": "6576685"}, {"title": "Great Britain in Egypt / by E. W. Polson Newman ; forword by Sir J. G. Maxwell.", "author": "Newman, E. W. Polson 1887-", "id": "1607931"}, {"title": "Le nationalisme \u00e9gyptien.", "author": "Georges-Gaulis, Berthe", "id": "6576695"}]