[{"title": "Die gestaltung der landschaft durch den menschen ...", "author": "Schultze-Naumburg, Paul, 1869-1949", "id": "2243295"}, {"title": "The new exploration; a philosophy of regional planning, by Benton MacKaye; illustrated with maps.", "author": "MacKaye, Benton, 1879-", "id": "1273817"}, {"title": "The new exploration; a philosophy of regional planning, by Benton MacKaye; illustrated with maps.", "author": "MacKaye, Benton, 1879-", "id": "1273817"}, {"title": "The new exploration; a philosophy of regional planning, by Benton MacKaye; illustrated with maps.", "author": "MacKaye, Benton, 1879-", "id": "1273817"}, {"title": "Begriff und Aufgaben der geographischen Rechtswissenschaft (Geojurisprudenz) : systematisches u\u0308ber die Beziehungen der Rechtswissenschaft zur Geographie, Kartographie und Geopolitik / Manfred Langhans-Ratzeburg.", "author": "Langhans, Manfred.", "id": "6084389"}, {"title": "Staat und Klima.", "author": "Burchard, Albrecht, 1888-1939.", "id": "8223905"}]