[{"title": "Descripcio\u0301n colonial / por Reginaldo de Liza\u0301rraga.", "author": "Liza\u0301rraga, Reginaldo de, ca. 1545-1615.", "id": "101501530"}, {"title": "Descripcio\u0301n colonial / por Reginaldo de Liza\u0301rraga.", "author": "Liza\u0301rraga, Reginaldo de, ca. 1545-1615.", "id": "101501530"}, {"title": "Mound builders of Illinois : descriptive of certain mounds and village sites in the American bottoms and along the Kaskaskia and Illinois rivers / by Addison J. Throop.", "author": "Throop, Addison James, 1876-", "id": "450671"}]