[{"title": "A dictionary of books relating to America from its discovery to the present time / begun by Joseph Sabin, and continued by Wilberforce Eames for the Bibliographical Society of America.", "author": "Sabin, Joseph, 1821-1881", "id": "100261707"}, {"title": "Narratives of captivity among the Indians of North America : a list of books and manuscripts on this subject in the Edward E. Ayer Collection of the Newberry Library : Supplement I / by Clara A. Smith ...", "author": "Edward E. Ayer Collection.", "id": "5998643"}, {"title": "Catalog of Copyright Entries. Part 1. [C] Group 3. Dramatic Composition and Motion Pictures. New Series", "author": "Library of Congress. Copyright Office.", "id": "10098747"}, {"title": "Catalog of Copyright Entries. Part 1. [B] Group 2. Pamphlets, Etc. New Series", "author": "Library of Congress. Copyright Office.", "id": "10100473"}, {"title": "Catalog of Copyright Entries. Part 1. [B] Group 2. Pamphlets, Etc. New Series", "author": "Library of Congress. Copyright Office.", "id": "10100473"}, {"title": "Catalog of copyright entries. Part 3, Musical compositions.", "author": "", "id": "10098746"}, {"title": "Catalog of copyright entries. Part 3, Musical compositions.", "author": "", "id": "10098746"}]