[{"title": "Les fonctions mentales dans les socie\u0301te\u0301s infe\u0301rieures / par L. Le\u0301vy-Bruhl.", "author": "Le\u0301vy-Bruhl, Lucien, 1857-1939.", "id": "6001514"}, {"title": "The \"soul\" of the primitive / by Lucien L\u00e9vy-Bruhl ... Authorized translation by Lilian A. Clare.", "author": "L\u00e9vy-Bruhl, Lucien, 1857-1939.", "id": "1879253"}, {"title": "La structure de la mentalit\u00e9 primitive, par G. van der Leeuw ...", "author": "Leeuw, G. van der 1890-1950.", "id": "1879248"}, {"title": "The \"soul\" of the primitive / by Lucien L\u00e9vy-Bruhl ... Authorized translation by Lilian A. Clare.", "author": "L\u00e9vy-Bruhl, Lucien, 1857-1939.", "id": "1879254"}, {"title": "Das Ritual; psychoanalytische Studien, mit einer Vorrede von Sigm. Freud.", "author": "Reik, Theodor, 1888-1969.", "id": "101949533"}]