[{"title": "Freud und Adler: elementare Einfu\u0308hrung in Psychoanalyse und Individualpsychologie, von dr. Alice Ru\u0308hle-Gerstel.", "author": "Ru\u0308hle-Gerstel, Alice, 1894-1943.", "id": "10604073"}, {"title": "Why men fail, edited by Morris Fishbein and William A. White.", "author": "Fishbein, Morris, 1889-1976.", "id": "619871"}, {"title": "The psychology of abnormal people, with educational applications, by John J. B. Morgan.", "author": "Morgan, John Jacob Brooke, 1888-", "id": "661296"}, {"title": "La psychanalyse; th\u00e9orie sexuelle de Freud.", "author": "Hesnard, Angelo Louis Marie, 1886-", "id": "658087"}, {"title": "Contributions to analytical psychology, by C. G. Jung. Translated by H. G. and Cary F. Baynes.", "author": "Jung, C. G. 1875-1961.", "id": "660452"}, {"title": "The International journal of psycho-analysis.", "author": "", "id": "69603"}, {"title": "Contributions to analytical psychology, by C. G. Jung. Translated by H. G. and Cary F. Baynes.", "author": "Jung, C. G. 1875-1961.", "id": "660452"}, {"title": "De l'angoisse a\u0300 l'extase ; e\u0301tudes sur les croyances et les sentiments, par le dr. Pierre Janet.", "author": "Janet, Pierre, 1859-1947.", "id": "660283"}, {"title": "La psychanalyse et les nouvelles m\u00e9thodes d'investigation de l'inconscient; \u00e9tude des probl\u00e8mes de l'inconscient au point de vue du d\u00e9terminisme psychanalyse.", "author": "Marie, Armand, 1865-", "id": "656308"}, {"title": "Revue fran\u00e7aise de psychanalyse.", "author": "", "id": "641473"}, {"title": "The experience variables: a study of the variable factors in experience contributing to the formation of personality, by Joseph O. Chassell.", "author": "Chassell, Joseph Olin, 1900-", "id": "618226"}, {"title": "Gesammelte schriften von Sigm. Freud...", "author": "Freud, Sigmund, 1856-1939.", "id": "7037712"}, {"title": "L'unite\u0301 psychique et les troubles mentaux.", "author": "Mignard, Maurice, 1881-1926.", "id": "7037317"}, {"title": "Gesammelte schriften von Sigm. Freud...", "author": "Freud, Sigmund, 1856-1939.", "id": "7037712"}, {"title": "Gesammelte schriften von Sigm. Freud...", "author": "Freud, Sigmund, 1856-1939.", "id": "7037712"}, {"title": "Gesammelte schriften von Sigm. Freud...", "author": "Freud, Sigmund, 1856-1939.", "id": "7037712"}, {"title": "Gesammelte schriften von Sigm. Freud...", "author": "Freud, Sigmund, 1856-1939.", "id": "7037712"}, {"title": "Gesammelte schriften von Sigm. Freud...", "author": "Freud, Sigmund, 1856-1939.", "id": "7037712"}, {"title": "Gesammelte schriften von Sigm. Freud...", "author": "Freud, Sigmund, 1856-1939.", "id": "7037712"}, {"title": "Gesammelte schriften von Sigm. Freud...", "author": "Freud, Sigmund, 1856-1939.", "id": "7037712"}, {"title": "Religiosita\u0308t und hysterie, von Dr. Oskar Pfister.", "author": "Pfister, Oskar, 1873-1956.", "id": "6499642"}, {"title": "Krisis der Psychoanalyse : systematische Diskussion der Lehre Freuds / herausgegeben von Hans Prinzhorn und Kuno Mittenzwey.", "author": "", "id": "9972629"}, {"title": "The motives of men, by George A. Coe ...", "author": "Coe, George Albert, 1862-1951.", "id": "8304387"}, {"title": "Contributions to analytical psychology, by C. G. Jung. Translated by H. G. and Cary F. Baynes.", "author": "Jung, C. G. 1875-1961.", "id": "660452"}, {"title": "Die Beziehungen zwischen dem Ich und dem Unbewussten.", "author": "Jung, C. G. 1875-1961.", "id": "6196166"}, {"title": "Das Christentum in der Geleuchtung der Psychoanalyse : Versuch einer Darstellung und Kritik der psychoanalytischen Aussagen \u00fcber das religi\u00f6se Erleben / Hans Saalfeld.", "author": "Saalfeld, Hans.", "id": "10274399"}, {"title": "Revue fran\u00e7aise de psychanalyse.", "author": "", "id": "641473"}, {"title": "Studies in psychology and psychiatry / Catholic University of America.", "author": "", "id": "9657680"}, {"title": "The inferiority feeling, by William S. Walsh.", "author": "Walsh, William Sebastian, b. 1890.", "id": "6196033"}, {"title": "Die Beziehungen zwischen dem Ich und dem Unbewussten.", "author": "Jung, C. G. 1875-1961.", "id": "6196166"}, {"title": "Studies in psychology and psychiatry / Catholic University of America.", "author": "", "id": "9657680"}, {"title": "Imago.", "author": "", "id": "100116801"}, {"title": "The motives of men, by George A. Coe ...", "author": "Coe, George Albert, 1862-1951.", "id": "8304387"}, {"title": "De l'angoisse a\u0300 l'extase ; e\u0301tudes sur les croyances et les sentiments, par le dr. Pierre Janet.", "author": "Janet, Pierre, 1859-1947.", "id": "660283"}, {"title": "De l'angoisse a\u0300 l'extase ; e\u0301tudes sur les croyances et les sentiments, par le dr. Pierre Janet.", "author": "Janet, Pierre, 1859-1947.", "id": "660283"}, {"title": "Morton Prince and abnormal psychology, by W.S. Taylor...", "author": "Taylor, William Sentman, 1894-", "id": "5767739"}]